pyspark_utils/__init__.py
pyspark_utils/stats.py
pysparkutilsag-0.3.0.dist-info/LICENSE
pysparkutilsag-0.3.0.dist-info/METADATA
pysparkutilsag-0.3.0.dist-info/WHEEL
pysparkutilsag-0.3.0.dist-info/top_level.txt
pysparkutilsag-0.3.0.dist-info/RECORD
